{
    "Du\u0161en\u00e9 vep\u0159ov\u00e9 na \u010desneku - Recept - Kaufland.cz": {
        "downloaded": true,
        "link": "https://prodejny.kaufland.cz/recepty/vyhledat-recept/recept.dusene-veprove-cesneku.r_id%3DCZ_2207.html",
        "rank_search_engine": 2,
        "title": "Du\u0161en\u00e9 vep\u0159ov\u00e9 na \u010desneku - Recept - Kaufland.cz"
    },
    "Kotlety na \u010desneku - Apetit Online": {
        "downloaded": true,
        "link": "https://www.apetitonline.cz/recept/kotlety-na-cesneku",
        "rank_search_engine": 6,
        "title": "Kotlety na \u010desneku - Apetit Online"
    },
    "Vep\u0159ov\u00e1 pe\u010den\u011b v \u010desneku a petr\u017eelce, \u0161pen\u00e1tov\u00e9 pyr\u00e9, restovan\u00e9 ...": {
        "downloaded": true,
        "link": "https://www.ceskatelevize.cz/porady/10084897100-kluci-v-akci/1137-recepty/12293-veprova-pecene-v-cesneku-a-petrzelce-spenatove-pyre-restovane-zampiony-s-rimskym-kminem-a-paprikove-brambory/",
        "rank_search_engine": 7,
        "title": "Vep\u0159ov\u00e1 pe\u010den\u011b v \u010desneku a petr\u017eelce, \u0161pen\u00e1tov\u00e9 pyr\u00e9, restovan\u00e9 ..."
    },
    "Vep\u0159ov\u00e9 maso na \u010desneku - TopRecepty.cz": {
        "downloaded": true,
        "link": "https://www.toprecepty.cz/recept/2543-veprove-maso-na-cesneku/",
        "rank_search_engine": 1,
        "title": "Vep\u0159ov\u00e9 maso na \u010desneku - TopRecepty.cz"
    },
    "Vep\u0159ov\u00e9 na \u010desneku - Recepty.cz - On-line kucha\u0159ka": {
        "downloaded": true,
        "link": "https://www.recepty.cz/recept/veprove-na-cesneku-151019",
        "rank_search_engine": 5,
        "title": "Vep\u0159ov\u00e9 na \u010desneku - Recepty.cz - On-line kucha\u0159ka"
    },
    "Vep\u0159ov\u00e9 na \u010desneku - TopRecepty.cz": {
        "downloaded": true,
        "link": "https://www.toprecepty.cz/recept/55242-veprove-na-cesneku/",
        "rank_search_engine": 3,
        "title": "Vep\u0159ov\u00e9 na \u010desneku - TopRecepty.cz"
    },
    "Vep\u0159ov\u00e9 pl\u00e1tky na v\u00edn\u011b - Albert": {
        "downloaded": true,
        "link": "https://www.albert.cz/recepty/veprove-platky-na-vine/r/a134588",
        "rank_search_engine": 8,
        "title": "Vep\u0159ov\u00e9 pl\u00e1tky na v\u00edn\u011b - Albert"
    },
    "Vep\u0159ov\u00fd jazyk na \u010desneku-recept - YouTube": {
        "downloaded": true,
        "link": "https://www.youtube.com/watch%3Fv%3DfXtGJJpTXNU",
        "rank_search_engine": 4,
        "title": "Vep\u0159ov\u00fd jazyk na \u010desneku-recept - YouTube"
    },
    "\u010cesnekov\u00e9 m\u00e1slo - Prima Fresh - iPrima": {
        "downloaded": true,
        "link": "https://fresh.iprima.cz/cesnekove-maslo",
        "rank_search_engine": 9,
        "title": "\u010cesnekov\u00e9 m\u00e1slo - Prima Fresh - iPrima"
    }
}